{
  "openapi": "3.1.0",
  "info": {
    "title": "",
    "version": ""
  },
  "paths": {
    "/v1/search/hashtags": {
      "get": {
        "tags": [
          "Search"
        ],
        "summary": "Search Hashtags",
        "description": "Search hashtags. Returns a list of matching results.",
        "operationId": "search_hashtags_v1_search_hashtags_get",
        "parameters": [
          {
            "name": "query",
            "in": "query",
            "required": true,
            "schema": {
              "type": "string",
              "title": "Query"
            }
          }
        ],
        "x-codeSamples": [
          {
            "lang": "Python",
            "source": "from hikerapi import Client\n\ncl = Client(<ACCESS_KEY>)\nres = await cl.search_hashtags_v1(query=\"love\")\n",
            "label": "Python"
          }
        ],
        "required": false
      }
    },
    "/v1/search/users": {
      "get": {
        "tags": [
          "Search"
        ],
        "summary": "It is recommended to use /v2/search/accounts as this endpoint will soon be deprecated.",
        "description": "Search users. Returns a list of matching results.",
        "operationId": "search_users_v1_search_users_get",
        "parameters": [
          {
            "name": "query",
            "in": "query",
            "required": true,
            "schema": {
              "type": "string",
              "title": "Query"
            }
          }
        ],
        "x-codeSamples": [
          {
            "lang": "Python",
            "source": "from hikerapi import Client\n\ncl = Client(<ACCESS_KEY>)\nres = await cl.search_users_v1(query=\"sun\")\n",
            "label": "Python"
          }
        ],
        "required": false
      }
    },
    "/v1/fbsearch/topsearch": {
      "get": {
        "tags": [
          "Search"
        ],
        "summary": "Fbsearch Topsearch",
        "description": "Topsearch. Returns a list of matching results.",
        "operationId": "fbsearch_topsearch_v1_fbsearch_topsearch_get",
        "parameters": [
          {
            "name": "query",
            "in": "query",
            "required": true,
            "schema": {
              "type": "string",
              "title": "Query"
            }
          }
        ],
        "x-codeSamples": [
          {
            "lang": "Python",
            "source": "from hikerapi import Client\n\ncl = Client(<ACCESS_KEY>)\nres = await cl.fbsearch_topsearch_v1(query=\"Berlin\")\n",
            "label": "Python"
          }
        ],
        "required": false
      }
    },
    "/v1/fbsearch/places": {
      "get": {
        "tags": [
          "Search"
        ],
        "summary": "Fbsearch Places",
        "description": "Search locations. Returns a list of matching results.",
        "operationId": "fbsearch_places_v1_fbsearch_places_get",
        "parameters": [
          {
            "name": "query",
            "in": "query",
            "required": true,
            "schema": {
              "type": "string",
              "title": "Query"
            }
          },
          {
            "name": "lat",
            "in": "query",
            "required": false,
            "schema": {
              "anyOf": [
                {
                  "type": "number"
                },
                {
                  "type": "null"
                }
              ],
              "default": 40.74,
              "title": "Lat"
            }
          },
          {
            "name": "lng",
            "in": "query",
            "required": false,
            "schema": {
              "anyOf": [
                {
                  "type": "number"
                },
                {
                  "type": "null"
                }
              ],
              "default": -73.94,
              "title": "Lng"
            }
          }
        ],
        "x-codeSamples": [
          {
            "lang": "Python",
            "source": "from hikerapi import Client\n\ncl = Client(<ACCESS_KEY>)\nres = await cl.fbsearch_places_v1(query=\"Berlin\", lat=None, lng=None)\n",
            "label": "Python"
          }
        ],
        "required": false
      }
    },
    "/v1/search/music": {
      "get": {
        "tags": [
          "Search"
        ],
        "summary": "Search Music",
        "description": "Search music. Returns a list of matching results.",
        "operationId": "search_music_v1_search_music_get",
        "parameters": [
          {
            "name": "query",
            "in": "query",
            "required": true,
            "schema": {
              "type": "string",
              "title": "Query"
            }
          }
        ],
        "x-codeSamples": [
          {
            "lang": "Python",
            "source": "from hikerapi import Client\n\ncl = Client(<ACCESS_KEY>)\nres = await cl.search_music_v1(query=\"rock\")\n",
            "label": "Python"
          }
        ],
        "required": false
      }
    },
    "/v1/fbsearch/topsearch/hashtags": {
      "get": {
        "tags": [
          "Search"
        ],
        "summary": "Web Search Topsearch Hashtags",
        "description": "Search hashtags via topsearch. Returns a list of matching results.",
        "operationId": "web_search_topsearch_hashtags_v1_fbsearch_topsearch_hashtags_get",
        "parameters": [
          {
            "name": "query",
            "in": "query",
            "required": true,
            "schema": {
              "type": "string",
              "title": "Query"
            }
          }
        ],
        "x-codeSamples": [
          {
            "lang": "Python",
            "source": "from hikerapi import Client\n\ncl = Client(<ACCESS_KEY>)\nres = await cl.fbsearch_topsearch_hashtags_v1(query=\"Berlin\")\n",
            "label": "Python"
          }
        ],
        "required": false
      }
    },
    "/v1/share/reel/by/url": {
      "get": {
        "tags": [
          "Share"
        ],
        "summary": "Works for reel (clips) only",
        "operationId": "share_reel_by_url_v1_share_reel_by_url_get",
        "parameters": [
          {
            "name": "url",
            "in": "query",
            "required": true,
            "schema": {
              "type": "string",
              "title": "Url"
            }
          }
        ],
        "x-codeSamples": [
          {
            "lang": "Python",
            "source": "from hikerapi import Client\n\ncl = Client(<ACCESS_KEY>)\nres = await cl.share_reel_by_url_v1(\n    url=\"https://www.instagram.com/share/reel/BBX9-xjv1r\"\n)\n",
            "label": "Python"
          }
        ],
        "required": false,
        "description": "Returns shared content data."
      }
    },
    "/v1/share/by/code": {
      "get": {
        "tags": [
          "Share"
        ],
        "summary": "Works for stories and highlights only or use (/v1/media/by/url, /v1/story/by/url)",
        "description": "Get share object by code (aGlnaGxpZ2h0OjE4MTQ2MjE2Njk4MDIyMTc0 ->\n{\"pk\": 18146216698022176, \"type\": \"highlight\"}). Returns shared content data.",
        "operationId": "share_by_code_v1_share_by_code_get",
        "parameters": [
          {
            "name": "code",
            "in": "query",
            "required": true,
            "schema": {
              "type": "string",
              "title": "Code"
            }
          }
        ],
        "x-codeSamples": [
          {
            "lang": "Python",
            "source": "from hikerapi import Client\n\ncl = Client(<ACCESS_KEY>)\nres = await cl.share_by_code_v1(code=\"aGlnaGxpZ2h0OjE4MTQ2MjE2Njk4MDIyMTc0\")\n",
            "label": "Python"
          }
        ],
        "required": false
      }
    },
    "/v1/share/by/url": {
      "get": {
        "tags": [
          "Share"
        ],
        "summary": "Works for stories and highlights only ig...m.com/s/aGln(link must contain /s/) or use (/v1/media/by/url, /v1/story/by/url)",
        "description": "Get share object by url (\nhttps://www.ins...ram.com/s/aGlnaGxpZ2h0OjE4MTQ2MjE2Njk4MDIyMTc0 ->\n{\"pk\": 18146216698022176, \"type\": \"highlight\"}). Returns shared content data.",
        "operationId": "share_by_url_v1_share_by_url_get",
        "parameters": [
          {
            "name": "url",
            "in": "query",
            "required": true,
            "schema": {
              "type": "string",
              "title": "Url"
            }
          }
        ],
        "x-codeSamples": [
          {
            "lang": "Python",
            "source": "from hikerapi import Client\n\ncl = Client(<ACCESS_KEY>)\nres = await cl.share_by_url_v1(\n    url=\"https://www.ins...ram.com/s/aGlnaGxpZ2h0OjE4MTQ2MjE2Njk4MDIyMTc0\"\n)\n",
            "label": "Python"
          }
        ],
        "required": false
      }
    }
  },
  "tags": [
    {
      "name": "Top 5",
      "description": "Most popular endpoints - start here"
    },
    {
      "name": "User Profile",
      "description": "Get user info, followers, following, posts & reels, stories",
      "externalDocs": {
        "description": "Documentation",
        "url": "https://hiker-doc.readthedocs.io/en/latest/python.html#hikerapi.AsyncClient.user_by_id_v1"
      }
    },
    {
      "name": "Post Details",
      "description": "Get media/post info by ID, code or URL. Likers, insights",
      "externalDocs": {
        "description": "Documentation",
        "url": "https://hiker-doc.readthedocs.io/en/latest/python.html#hikerapi.AsyncClient.media_by_id_v1"
      }
    },
    {
      "name": "Comments",
      "description": "Get comments on posts, comment likers, replies",
      "externalDocs": {
        "description": "Documentation",
        "url": "https://hiker-doc.readthedocs.io/en/latest/python.html#hikerapi.AsyncClient.media_comments_v1"
      }
    },
    {
      "name": "Search",
      "description": "Search users, hashtags, locations, music",
      "externalDocs": {
        "description": "Documentation",
        "url": "https://hiker-doc.readthedocs.io/en/latest/python.html#hikerapi.AsyncClient.search_hashtags_v1"
      }
    },
    {
      "name": "Hashtags",
      "description": "Get hashtag info and medias (top, recent, clips)",
      "externalDocs": {
        "description": "Documentation",
        "url": "https://hiker-doc.readthedocs.io/en/latest/python.html#hikerapi.AsyncClient.hashtag_by_name_v1"
      }
    },
    {
      "name": "Audio",
      "description": "Music and audio related endpoints",
      "externalDocs": {
        "description": "Documentation",
        "url": "https://hiker-doc.readthedocs.io/en/latest/python.html#hikerapi.AsyncClient.track_by_canonical_id_v2"
      }
    },
    {
      "name": "Location",
      "description": "Location info and medias",
      "externalDocs": {
        "description": "Documentation",
        "url": "https://hiker-doc.readthedocs.io/en/latest/python.html#hikerapi.AsyncClient.location_by_id_v1"
      }
    },
    {
      "name": "Stories",
      "description": "Stories by ID/URL, story download",
      "externalDocs": {
        "description": "Documentation",
        "url": "https://hiker-doc.readthedocs.io/en/latest/python.html#hikerapi.AsyncClient.story_by_id_v1"
      }
    },
    {
      "name": "Highlights",
      "description": "Highlights by ID/URL",
      "externalDocs": {
        "description": "Documentation",
        "url": "https://hiker-doc.readthedocs.io/en/latest/python.html#hikerapi.AsyncClient.highlight_by_id_v1"
      }
    },
    {
      "name": "Share",
      "description": "Resolve share links (/s/, /reel/ URLs)",
      "externalDocs": {
        "description": "Documentation",
        "url": "https://hiker-doc.readthedocs.io/en/latest/python.html"
      }
    },
    {
      "name": "System",
      "description": "System endpoints, balance, health checks",
      "externalDocs": {
        "description": "Documentation",
        "url": "https://hiker-doc.readthedocs.io/en/latest/python.html"
      }
    },
    {
      "name": "Legacy",
      "description": "Deprecated - use recommended alternatives"
    }
  ],
  "externalDocs": {
    "description": "Get the access_key",
    "url": "https://hikerapi.com/tokens"
  }
}
